gerapy_redis/__init__.py
gerapy_redis/__version__.py
gerapy_redis/connection.py
gerapy_redis/defaults.py
gerapy_redis/dupefilter.py
gerapy_redis/picklecompat.py
gerapy_redis/pipelines.py
gerapy_redis/queue.py
gerapy_redis/scheduler.py
gerapy_redis/stats.py
gerapy_redis/utils.py
gerapy_redis-0.1.1.dist-info/METADATA
gerapy_redis-0.1.1.dist-info/WHEEL
gerapy_redis-0.1.1.dist-info/top_level.txt
gerapy_redis-0.1.1.dist-info/RECORD
