Metadata-Version: 2.1
Name: gerapy-redis
Version: 0.1.1
Summary: Distribution Support for Scrapy & Gerapy using Redis
Home-page: https://github.com/Gerapy/GerapyRedis
Author: Germey
Author-email: cqc@cuiqingcai.com
License: MIT
Platform: UNKNOWN
Classifier: License :: OSI Approved :: MIT License
Classifier: Programming Language :: Python :: 3.5
Classifier: Programming Language :: Python :: 3.6
Classifier: Programming Language :: Python :: 3.7
Classifier: Programming Language :: Python :: 3.8
Classifier: Programming Language :: Python :: Implementation :: CPython
Classifier: Programming Language :: Python :: Implementation :: PyPy
Requires-Python: >=3.5.0
Requires-Dist: scrapy (>=1.0.0)
Requires-Dist: redis (<=2.10.6,>=2.10.0)
Requires-Dist: six (>=1.5.2)
